stepist/__init__.py
stepist/app.py
stepist/app_config.py
stepist/dbs.py
stepist/flow/__init__.py
stepist/flow/session.py
stepist/flow/signals.py
stepist/flow/utils.py
stepist/flow/libs/__init__.py
stepist/flow/libs/simple_queue.py
stepist/flow/stats/__init__.py
stepist/flow/stats/utils.py
stepist/flow/stats/worker.py
stepist/flow/steps/__init__.py
stepist/flow/steps/factory_step.py
stepist/flow/steps/hub.py
stepist/flow/steps/next_step.py
stepist/flow/steps/reducer_step.py
stepist/flow/steps/step.py
stepist/flow/workers/__init__.py
stepist/flow/workers/reducer_engine.py
stepist/flow/workers/utils.py
stepist/flow/workers/worker_engine.py
stepist/flow/workers/adapters/__init__.py
stepist/flow/workers/adapters/celery_queue.py
stepist/flow/workers/adapters/rm_queue.py
stepist/flow/workers/adapters/simple_queue.py
stepist/flow/workers/adapters/sqs_queue.py
stepist/flow/workers/adapters/utils.py
stepist/flow/workers/boost/__init__.py
stepist/flow/workers/boost/shared_memory.py
stepist/flow/workers/boost/sockets.py
stepist/tests/.DS_Store
stepist-0.1.6.1.dist-info/METADATA
stepist-0.1.6.1.dist-info/WHEEL
stepist-0.1.6.1.dist-info/top_level.txt
stepist-0.1.6.1.dist-info/RECORD
