Metadata-Version: 2.1
Name: stepist
Version: 0.1.6.1
Summary: Data process utils
Home-page: https://github.com/electronick1/stepist
Author: Aleh Shydlouski
Author-email: oleg.ivye@gmail.com
License: UNKNOWN
Download-URL: https://github.com/electronick1/stepist/archive/0.1.6.1.tar.gz
Keywords: data,ai,distribute
Platform: UNKNOWN
Requires-Dist: tqdm
Requires-Dist: redis (>=3.0.0)
Requires-Dist: blinker
Requires-Dist: click
Requires-Dist: ujson (>=1.0)
